LICENSE
MANIFEST.in
README.rst
setup.cfg
setup.py
cart/__init__.py
cart/admin.py
cart/apps.py
cart/cart.py
cart/context_processor.py
cart/models.py
cart/tests.py
cart/urls.py
cart/views.py
cartAMDI.egg-info/PKG-INFO
cartAMDI.egg-info/SOURCES.txt
cartAMDI.egg-info/dependency_links.txt
cartAMDI.egg-info/top_level.txt
cart/migrations/__init__.py
cart/templatetags/__init__.py
cart/templatetags/cart_tag.py